<?xml version="1.0" encoding="UTF-8"?>
<Annotation>
    <folder>MV12_0604_d</folder>
    <subfolder>thermal</subfolder>
    <filename>MV12_THERMAL_190604_220201_09.png</filename>
    <environment>
        <camerastate>MV</camerastate>
        <weather>Sunny</weather>
        <venue>Po-hang</venue>
        <purpose>Detection</purpose>
    </environment>
    <size>
        <width>640</width>
        <height>512</height>
        <depth>3</depth>
    </size>
    <object>
        <name>Human</name>
        <pose>sit</pose>
        <bndbox>
            <xmin>-3</xmin>
            <ymin>22</ymin>
            <xmax>150</xmax>
            <ymax>299</ymax>
        </bndbox>
    </object>
    <object>
        <name>Human</name>
        <pose>stand</pose>
        <bndbox>
            <xmin>321</xmin>
            <ymin>228</ymin>
            <xmax>348</xmax>
            <ymax>320</ymax>
        </bndbox>
    </object>
    <object>
        <name>Human</name>
        <pose>stand</pose>
        <bndbox>
            <xmin>533</xmin>
            <ymin>166</ymin>
            <xmax>607</xmax>
            <ymax>423</ymax>
        </bndbox>
    </object>
    <object>
        <name>Human</name>
        <pose>sit</pose>
        <bndbox>
            <xmin>167</xmin>
            <ymin>221</ymin>
            <xmax>205</xmax>
            <ymax>273</ymax>
        </bndbox>
    </object>
    <object>
        <name>Human</name>
        <pose>sit</pose>
        <bndbox>
            <xmin>265</xmin>
            <ymin>232</ymin>
            <xmax>301</xmax>
            <ymax>266</ymax>
        </bndbox>
    </object>
    <object>
        <name>Human</name>
        <pose>sit</pose>
        <bndbox>
            <xmin>8</xmin>
            <ymin>186</ymin>
            <xmax>101</xmax>
            <ymax>334</ymax>
        </bndbox>
    </object>
    <object>
        <name>Human</name>
        <pose>stand</pose>
        <bndbox>
            <xmin>303</xmin>
            <ymin>233</ymin>
            <xmax>326</xmax>
            <ymax>312</ymax>
        </bndbox>
    </object>
    <object>
        <name>Human</name>
        <pose>lie</pose>
        <bndbox>
            <xmin>316</xmin>
            <ymin>212</ymin>
            <xmax>427</xmax>
            <ymax>240</ymax>
        </bndbox>
    </object>
    <object>
        <name>Human</name>
        <pose>lie</pose>
        <bndbox>
            <xmin>414</xmin>
            <ymin>198</ymin>
            <xmax>554</xmax>
            <ymax>233</ymax>
        </bndbox>
    </object>
</Annotation>
