<?xml version="1.0" encoding="UTF-8"?>
<Annotation>
    <folder>MV12_0604_d</folder>
    <subfolder>thermal</subfolder>
    <filename>MV12_THERMAL_190604_220620_06.png</filename>
    <environment>
        <camerastate>MV</camerastate>
        <weather>Sunny</weather>
        <venue>Po-hang</venue>
        <purpose>Detection</purpose>
    </environment>
    <size>
        <width>640</width>
        <height>512</height>
        <depth>3</depth>
    </size>
    <object>
        <name>Human</name>
        <pose>sit</pose>
        <bndbox>
            <xmin>309</xmin>
            <ymin>235</ymin>
            <xmax>342</xmax>
            <ymax>276</ymax>
        </bndbox>
    </object>
    <object>
        <name>Human</name>
        <pose>sit</pose>
        <bndbox>
            <xmin>237</xmin>
            <ymin>233</ymin>
            <xmax>281</xmax>
            <ymax>273</ymax>
        </bndbox>
    </object>
    <object>
        <name>Human</name>
        <pose>lie</pose>
        <bndbox>
            <xmin>189</xmin>
            <ymin>240</ymin>
            <xmax>216</xmax>
            <ymax>265</ymax>
        </bndbox>
    </object>
    <object>
        <name>Human</name>
        <pose>stand</pose>
        <bndbox>
            <xmin>273</xmin>
            <ymin>243</ymin>
            <xmax>296</xmax>
            <ymax>288</ymax>
        </bndbox>
    </object>
    <object>
        <name>Human</name>
        <pose>lie</pose>
        <bndbox>
            <xmin>106</xmin>
            <ymin>238</ymin>
            <xmax>147</xmax>
            <ymax>265</ymax>
        </bndbox>
    </object>
    <object>
        <name>Human</name>
        <pose>sit</pose>
        <bndbox>
            <xmin>48</xmin>
            <ymin>245</ymin>
            <xmax>80</xmax>
            <ymax>270</ymax>
        </bndbox>
    </object>
    <object>
        <name>Human</name>
        <pose>stand</pose>
        <bndbox>
            <xmin>81</xmin>
            <ymin>248</ymin>
            <xmax>102</xmax>
            <ymax>290</ymax>
        </bndbox>
    </object>
    <object>
        <name>Human</name>
        <pose>stand</pose>
        <bndbox>
            <xmin>61</xmin>
            <ymin>253</ymin>
            <xmax>79</xmax>
            <ymax>293</ymax>
        </bndbox>
    </object>
    <object>
        <name>Human</name>
        <pose>stand</pose>
        <bndbox>
            <xmin>26</xmin>
            <ymin>249</ymin>
            <xmax>48</xmax>
            <ymax>288</ymax>
        </bndbox>
    </object>
</Annotation>
