<?xml version="1.0" encoding="UTF-8"?>
<Annotation>
    <folder>MV12_0604_d</folder>
    <subfolder>thermal</subfolder>
    <filename>MV12_THERMAL_190604_220118_01.png</filename>
    <environment>
        <camerastate>MV</camerastate>
        <weather>Sunny</weather>
        <venue>Po-hang</venue>
        <purpose>Detection</purpose>
    </environment>
    <size>
        <width>640</width>
        <height>512</height>
        <depth>3</depth>
    </size>
    <object>
        <name>Human</name>
        <pose>sit</pose>
        <bndbox>
            <xmin>180</xmin>
            <ymin>203</ymin>
            <xmax>244</xmax>
            <ymax>291</ymax>
        </bndbox>
    </object>
    <object>
        <name>Human</name>
        <pose>sit</pose>
        <bndbox>
            <xmin>9</xmin>
            <ymin>117</ymin>
            <xmax>191</xmax>
            <ymax>302</ymax>
        </bndbox>
    </object>
    <object>
        <name>Human</name>
        <pose>lie</pose>
        <bndbox>
            <xmin>522</xmin>
            <ymin>62</ymin>
            <xmax>640</xmax>
            <ymax>213</ymax>
        </bndbox>
    </object>
</Annotation>
