<?xml version="1.0" encoding="UTF-8"?>
<Annotation>
    <folder>MV12_0604_d</folder>
    <subfolder>thermal</subfolder>
    <filename>MV12_THERMAL_190604_220058_05.png</filename>
    <environment>
        <camerastate>MV</camerastate>
        <weather>Sunny</weather>
        <venue>Po-hang</venue>
        <purpose>Detection</purpose>
    </environment>
    <size>
        <width>640</width>
        <height>512</height>
        <depth>3</depth>
    </size>
    <object>
        <name>Human</name>
        <pose>walking</pose>
        <bndbox>
            <xmin>414</xmin>
            <ymin>198</ymin>
            <xmax>462</xmax>
            <ymax>333</ymax>
        </bndbox>
    </object>
    <object>
        <name>Human</name>
        <pose>lie</pose>
        <bndbox>
            <xmin>42</xmin>
            <ymin>125</ymin>
            <xmax>190</xmax>
            <ymax>235</ymax>
        </bndbox>
    </object>
    <object>
        <name>Human</name>
        <pose>sit</pose>
        <bndbox>
            <xmin>221</xmin>
            <ymin>204</ymin>
            <xmax>287</xmax>
            <ymax>267</ymax>
        </bndbox>
    </object>
    <object>
        <name>Human</name>
        <pose>stand</pose>
        <bndbox>
            <xmin>303</xmin>
            <ymin>239</ymin>
            <xmax>326</xmax>
            <ymax>295</ymax>
        </bndbox>
    </object>
    <object>
        <name>Human</name>
        <pose>lie</pose>
        <bndbox>
            <xmin>299</xmin>
            <ymin>226</ymin>
            <xmax>349</xmax>
            <ymax>242</ymax>
        </bndbox>
    </object>
    <object>
        <name>Human</name>
        <pose>lie</pose>
        <bndbox>
            <xmin>186</xmin>
            <ymin>182</ymin>
            <xmax>262</xmax>
            <ymax>260</ymax>
        </bndbox>
    </object>
    <object>
        <name>Human</name>
        <pose>walking</pose>
        <bndbox>
            <xmin>360</xmin>
            <ymin>230</ymin>
            <xmax>391</xmax>
            <ymax>299</ymax>
        </bndbox>
    </object>
    <object>
        <name>Human</name>
        <pose>lie</pose>
        <bndbox>
            <xmin>475</xmin>
            <ymin>216</ymin>
            <xmax>549</xmax>
            <ymax>278</ymax>
        </bndbox>
    </object>
</Annotation>
