<?xml version="1.0" encoding="UTF-8"?>
<Annotation>
    <folder>MV12_0604_d</folder>
    <subfolder>thermal</subfolder>
    <filename>MV12_THERMAL_190604_221153_03.png</filename>
    <environment>
        <camerastate>MV</camerastate>
        <weather>Sunny</weather>
        <venue>Po-hang</venue>
        <purpose>Detection</purpose>
    </environment>
    <size>
        <width>640</width>
        <height>512</height>
        <depth>3</depth>
    </size>
    <object>
        <name>Human</name>
        <pose>walking</pose>
        <bndbox>
            <xmin>498</xmin>
            <ymin>183</ymin>
            <xmax>568</xmax>
            <ymax>369</ymax>
        </bndbox>
    </object>
    <object>
        <name>Human</name>
        <pose>walking</pose>
        <bndbox>
            <xmin>331</xmin>
            <ymin>139</ymin>
            <xmax>436</xmax>
            <ymax>443</ymax>
        </bndbox>
    </object>
    <object>
        <name>Human</name>
        <pose>walking</pose>
        <bndbox>
            <xmin>196</xmin>
            <ymin>149</ymin>
            <xmax>305</xmax>
            <ymax>420</ymax>
        </bndbox>
    </object>
    <object>
        <name>Human</name>
        <pose>walking</pose>
        <bndbox>
            <xmin>576</xmin>
            <ymin>182</ymin>
            <xmax>629</xmax>
            <ymax>349</ymax>
        </bndbox>
    </object>
    <object>
        <name>Human</name>
        <pose>walking</pose>
        <bndbox>
            <xmin>326</xmin>
            <ymin>203</ymin>
            <xmax>367</xmax>
            <ymax>351</ymax>
        </bndbox>
    </object>
</Annotation>
