<?xml version="1.0" encoding="UTF-8"?>
<Annotation>
    <folder>MV12_0604_d</folder>
    <subfolder>thermal</subfolder>
    <filename>MV12_THERMAL_190604_221225_09.png</filename>
    <environment>
        <camerastate>MV</camerastate>
        <weather>Sunny</weather>
        <venue>Po-hang</venue>
        <purpose>Detection</purpose>
    </environment>
    <size>
        <width>640</width>
        <height>512</height>
        <depth>3</depth>
    </size>
    <object>
        <name>Human</name>
        <pose>walking</pose>
        <bndbox>
            <xmin>245</xmin>
            <ymin>228</ymin>
            <xmax>262</xmax>
            <ymax>300</ymax>
        </bndbox>
    </object>
    <object>
        <name>Human</name>
        <pose>walking</pose>
        <bndbox>
            <xmin>228</xmin>
            <ymin>225</ymin>
            <xmax>253</xmax>
            <ymax>302</ymax>
        </bndbox>
    </object>
    <object>
        <name>Human</name>
        <pose>walking</pose>
        <bndbox>
            <xmin>259</xmin>
            <ymin>228</ymin>
            <xmax>282</xmax>
            <ymax>298</ymax>
        </bndbox>
    </object>
    <object>
        <name>Human</name>
        <pose>stand</pose>
        <bndbox>
            <xmin>581</xmin>
            <ymin>238</ymin>
            <xmax>604</xmax>
            <ymax>302</ymax>
        </bndbox>
    </object>
    <object>
        <name>Human</name>
        <pose>walking</pose>
        <bndbox>
            <xmin>202</xmin>
            <ymin>241</ymin>
            <xmax>214</xmax>
            <ymax>281</ymax>
        </bndbox>
    </object>
    <object>
        <name>Human</name>
        <pose>walking</pose>
        <bndbox>
            <xmin>208</xmin>
            <ymin>228</ymin>
            <xmax>233</xmax>
            <ymax>299</ymax>
        </bndbox>
    </object>
    <object>
        <name>Human</name>
        <pose>stand</pose>
        <bndbox>
            <xmin>550</xmin>
            <ymin>235</ymin>
            <xmax>576</xmax>
            <ymax>302</ymax>
        </bndbox>
    </object>
    <object>
        <name>Human</name>
        <pose>walking</pose>
        <bndbox>
            <xmin>192</xmin>
            <ymin>244</ymin>
            <xmax>205</xmax>
            <ymax>274</ymax>
        </bndbox>
    </object>
</Annotation>
