<?xml version="1.0" encoding="UTF-8"?>
<Annotation>
    <folder>MV12_0604_d</folder>
    <subfolder>thermal</subfolder>
    <filename>MV12_THERMAL_190604_220026_05.png</filename>
    <environment>
        <camerastate>MV</camerastate>
        <weather>Sunny</weather>
        <venue>Po-hang</venue>
        <purpose>Detection</purpose>
    </environment>
    <size>
        <width>640</width>
        <height>512</height>
        <depth>3</depth>
    </size>
    <object>
        <name>Human</name>
        <pose>sit</pose>
        <bndbox>
            <xmin>309</xmin>
            <ymin>223</ymin>
            <xmax>348</xmax>
            <ymax>287</ymax>
        </bndbox>
    </object>
    <object>
        <name>Human</name>
        <pose>walking</pose>
        <bndbox>
            <xmin>228</xmin>
            <ymin>239</ymin>
            <xmax>243</xmax>
            <ymax>298</ymax>
        </bndbox>
    </object>
    <object>
        <name>Human</name>
        <pose>sitting</pose>
        <bndbox>
            <xmin>214</xmin>
            <ymin>241</ymin>
            <xmax>232</xmax>
            <ymax>293</ymax>
        </bndbox>
    </object>
    <object>
        <name>Human</name>
        <pose>walking</pose>
        <bndbox>
            <xmin>171</xmin>
            <ymin>241</ymin>
            <xmax>195</xmax>
            <ymax>293</ymax>
        </bndbox>
    </object>
    <object>
        <name>Human</name>
        <pose>walking</pose>
        <bndbox>
            <xmin>138</xmin>
            <ymin>246</ymin>
            <xmax>160</xmax>
            <ymax>292</ymax>
        </bndbox>
    </object>
    <object>
        <name>Human</name>
        <pose>sit</pose>
        <bndbox>
            <xmin>105</xmin>
            <ymin>240</ymin>
            <xmax>128</xmax>
            <ymax>269</ymax>
        </bndbox>
    </object>
</Annotation>
