<?xml version="1.0" encoding="UTF-8"?>
<Annotation>
    <folder>MV12_0604_d</folder>
    <subfolder>thermal</subfolder>
    <filename>MV12_THERMAL_190604_221252_05.png</filename>
    <environment>
        <camerastate>MV</camerastate>
        <weather>Sunny</weather>
        <venue>Po-hang</venue>
        <purpose>Detection</purpose>
    </environment>
    <size>
        <width>640</width>
        <height>512</height>
        <depth>3</depth>
    </size>
    <object>
        <name>Human</name>
        <pose>walking</pose>
        <bndbox>
            <xmin>451</xmin>
            <ymin>234</ymin>
            <xmax>468</xmax>
            <ymax>289</ymax>
        </bndbox>
    </object>
    <object>
        <name>Human</name>
        <pose>walking</pose>
        <bndbox>
            <xmin>401</xmin>
            <ymin>241</ymin>
            <xmax>427</xmax>
            <ymax>296</ymax>
        </bndbox>
    </object>
    <object>
        <name>Human</name>
        <pose>walking</pose>
        <bndbox>
            <xmin>380</xmin>
            <ymin>238</ymin>
            <xmax>401</xmax>
            <ymax>296</ymax>
        </bndbox>
    </object>
    <object>
        <name>Human</name>
        <pose>walking</pose>
        <bndbox>
            <xmin>354</xmin>
            <ymin>240</ymin>
            <xmax>379</xmax>
            <ymax>292</ymax>
        </bndbox>
    </object>
    <object>
        <name>Human</name>
        <pose>walking</pose>
        <bndbox>
            <xmin>351</xmin>
            <ymin>240</ymin>
            <xmax>363</xmax>
            <ymax>289</ymax>
        </bndbox>
    </object>
    <object>
        <name>Human</name>
        <pose>walking</pose>
        <bndbox>
            <xmin>476</xmin>
            <ymin>250</ymin>
            <xmax>486</xmax>
            <ymax>276</ymax>
        </bndbox>
    </object>
    <object>
        <name>Human</name>
        <pose>walking</pose>
        <bndbox>
            <xmin>441</xmin>
            <ymin>251</ymin>
            <xmax>447</xmax>
            <ymax>276</ymax>
        </bndbox>
    </object>
</Annotation>
