<?xml version="1.0" encoding="UTF-8"?>
<Annotation>
    <folder>MV12_0604_d</folder>
    <subfolder>thermal</subfolder>
    <filename>MV12_THERMAL_190604_220617_02.png</filename>
    <environment>
        <camerastate>MV</camerastate>
        <weather>Sunny</weather>
        <venue>Po-hang</venue>
        <purpose>Detection</purpose>
    </environment>
    <size>
        <width>640</width>
        <height>512</height>
        <depth>3</depth>
    </size>
    <object>
        <name>Human</name>
        <pose>sitting</pose>
        <bndbox>
            <xmin>311</xmin>
            <ymin>232</ymin>
            <xmax>344</xmax>
            <ymax>284</ymax>
        </bndbox>
    </object>
    <object>
        <name>Human</name>
        <pose>sit</pose>
        <bndbox>
            <xmin>245</xmin>
            <ymin>237</ymin>
            <xmax>286</xmax>
            <ymax>272</ymax>
        </bndbox>
    </object>
    <object>
        <name>Human</name>
        <pose>lie</pose>
        <bndbox>
            <xmin>202</xmin>
            <ymin>237</ymin>
            <xmax>226</xmax>
            <ymax>262</ymax>
        </bndbox>
    </object>
    <object>
        <name>Human</name>
        <pose>stand</pose>
        <bndbox>
            <xmin>276</xmin>
            <ymin>243</ymin>
            <xmax>299</xmax>
            <ymax>288</ymax>
        </bndbox>
    </object>
    <object>
        <name>Human</name>
        <pose>lie</pose>
        <bndbox>
            <xmin>113</xmin>
            <ymin>241</ymin>
            <xmax>154</xmax>
            <ymax>268</ymax>
        </bndbox>
    </object>
    <object>
        <name>Human</name>
        <pose>sit</pose>
        <bndbox>
            <xmin>64</xmin>
            <ymin>240</ymin>
            <xmax>96</xmax>
            <ymax>265</ymax>
        </bndbox>
    </object>
    <object>
        <name>Human</name>
        <pose>stand</pose>
        <bndbox>
            <xmin>105</xmin>
            <ymin>249</ymin>
            <xmax>126</xmax>
            <ymax>291</ymax>
        </bndbox>
    </object>
    <object>
        <name>Human</name>
        <pose>stand</pose>
        <bndbox>
            <xmin>72</xmin>
            <ymin>245</ymin>
            <xmax>90</xmax>
            <ymax>285</ymax>
        </bndbox>
    </object>
    <object>
        <name>Human</name>
        <pose>stand</pose>
        <bndbox>
            <xmin>37</xmin>
            <ymin>250</ymin>
            <xmax>59</xmax>
            <ymax>289</ymax>
        </bndbox>
    </object>
</Annotation>
