<?xml version="1.0" encoding="UTF-8"?>
<Annotation>
    <folder>MV12_0604_d</folder>
    <subfolder>thermal</subfolder>
    <filename>MV12_THERMAL_190604_220825_04.png</filename>
    <environment>
        <camerastate>MV</camerastate>
        <weather>Sunny</weather>
        <venue>Po-hang</venue>
        <purpose>Detection</purpose>
    </environment>
    <size>
        <width>640</width>
        <height>512</height>
        <depth>3</depth>
    </size>
    <object>
        <name>Human</name>
        <pose>walking</pose>
        <bndbox>
            <xmin>71</xmin>
            <ymin>238</ymin>
            <xmax>88</xmax>
            <ymax>287</ymax>
        </bndbox>
    </object>
    <object>
        <name>Human</name>
        <pose>stand</pose>
        <bndbox>
            <xmin>106</xmin>
            <ymin>240</ymin>
            <xmax>121</xmax>
            <ymax>282</ymax>
        </bndbox>
    </object>
    <object>
        <name>Human</name>
        <pose>stand</pose>
        <bndbox>
            <xmin>142</xmin>
            <ymin>233</ymin>
            <xmax>161</xmax>
            <ymax>295</ymax>
        </bndbox>
    </object>
    <object>
        <name>Human</name>
        <pose>stand</pose>
        <bndbox>
            <xmin>236</xmin>
            <ymin>247</ymin>
            <xmax>257</xmax>
            <ymax>298</ymax>
        </bndbox>
    </object>
    <object>
        <name>Human</name>
        <pose>sit</pose>
        <bndbox>
            <xmin>187</xmin>
            <ymin>229</ymin>
            <xmax>218</xmax>
            <ymax>275</ymax>
        </bndbox>
    </object>
    <object>
        <name>Human</name>
        <pose>sit</pose>
        <bndbox>
            <xmin>170</xmin>
            <ymin>242</ymin>
            <xmax>196</xmax>
            <ymax>268</ymax>
        </bndbox>
    </object>
    <object>
        <name>Human</name>
        <pose>sitting</pose>
        <bndbox>
            <xmin>419</xmin>
            <ymin>240</ymin>
            <xmax>455</xmax>
            <ymax>282</ymax>
        </bndbox>
    </object>
    <object>
        <name>Human</name>
        <pose>walking</pose>
        <bndbox>
            <xmin>498</xmin>
            <ymin>218</ymin>
            <xmax>544</xmax>
            <ymax>356</ymax>
        </bndbox>
    </object>
    <object>
        <name>Human</name>
        <pose>walking</pose>
        <bndbox>
            <xmin>268</xmin>
            <ymin>167</ymin>
            <xmax>345</xmax>
            <ymax>399</ymax>
        </bndbox>
    </object>
    <object>
        <name>Human</name>
        <pose>lie</pose>
        <bndbox>
            <xmin>540</xmin>
            <ymin>229</ymin>
            <xmax>611</xmax>
            <ymax>262</ymax>
        </bndbox>
    </object>
    <object>
        <name>Human</name>
        <pose>walking</pose>
        <bndbox>
            <xmin>592</xmin>
            <ymin>208</ymin>
            <xmax>632</xmax>
            <ymax>364</ymax>
        </bndbox>
    </object>
</Annotation>
